rkkr/__init__.py
rkkr/main.py
rkkr-2.1.6.dist-info/METADATA
rkkr-2.1.6.dist-info/WHEEL
rkkr-2.1.6.dist-info/top_level.txt
rkkr-2.1.6.dist-info/RECORD
