Metadata-Version: 2.1
Name: rkkr
Version: 2.1.6
Requires-Dist: keras
Requires-Dist: keras-tuner
Requires-Dist: pandas
Requires-Dist: numpy
Requires-Dist: scikit-learn
Requires-Dist: plotly
